{
  "schema": "cs2-categories/v1",
  "classes": {
    "AudioOps": [
      "sound_distancefocusfilter_setparams",
      "sound_group_start",
      "sound_group_stop",
      "sound_jingle",
      "sound_jingle_volume",
      "sound_mixbuss_add",
      "sound_mixbuss_setlevel",
      "sound_song",
      "sound_song_stop",
      "sound_song_volume",
      "sound_speech_volume",
      "sound_synth",
      "sound_synth_rate",
      "sound_synth_volume",
      "sound_vorbis_rate",
      "sound_vorbis_volume",
      "sound_vorbis_volume_rate_group"
    ],
    "CamOps": [
      "cam2_addeffect_shake",
      "cam2_addeffect_ztilt",
      "cam2_enable",
      "cam2_getcontrolmode",
      "cam2_getlookatmode",
      "cam2_getpositionentity_angleoffsets",
      "cam2_getpositionentity_lookatangle",
      "cam2_getpositionentity_lookatangleoffsets",
      "cam2_getpositionentity_lookatdistance",
      "cam2_getpositionmode",
      "cam2_getpositionpoint_point",
      "cam2_isenabled",
      "cam2_legacycam_ready",
      "cam2_removealleffects",
      "cam2_removeeffect",
      "cam2_resetsnapdistances",
      "cam2_setcollisionmode",
      "cam2_setdepthplanes",
      "cam2_setfieldofview",
      "cam2_setfieldofviewscreen",
      "cam2_setlinearmovementmode",
      "cam2_setlookatacceleration",
      "cam2_setlookatacceleration_axis",
      "cam2_setlookatangularinterpolation",
      "cam2_setlookatentity_npc",
      "cam2_setlookatentity_player",
      "cam2_setlookatmaxspeed",
      "cam2_setlookatmaxspeed_axis",
      "cam2_setlookatmode",
      "cam2_setlookatorientation_maxdistanceclamping",
      "cam2_setlookatorientation_vector",
      "cam2_setlookatorientation_xmovement",
      "cam2_setlookatorientation_xrotation",
      "cam2_setlookatorientation_yrotation",
      "cam2_setlookatorientation_zmovement",
      "cam2_setlookatpoint_point",
      "cam2_setlookatspline_spline",
      "cam2_setlookatspringproperties",
      "cam2_setpositionacceleration",
      "cam2_setpositionacceleration_axis",
      "cam2_setpositionangularinterpolation",
      "cam2_setpositionentity_npc",
      "cam2_setpositionentity_player",
      "cam2_setpositionmaxspeed",
      "cam2_setpositionmaxspeed_axis",
      "cam2_setpositionmode",
      "cam2_setpositionpoint_point",
      "cam2_setpositionpointcollision",
      "cam2_setpositionspline_spline",
      "cam2_setpositionspringproperties",
      "cam2_setsnapdistances",
      "cam2_setspringproperties",
      "cam2_settraildistance",
      "cam2_updateeffect_ztilt",
      "cam_dec_x",
      "cam_dec_y",
      "cam_followcoord",
      "cam_forceangle",
      "cam_getangle_xa",
      "cam_getangle_ya",
      "cam_getfollowheight",
      "cam_inc_x",
      "cam_inc_y",
      "cam_lookat",
      "cam_modeisfollowplayer",
      "cam_movealong",
      "cam_moveto",
      "cam_removeroof",
      "cam_reset",
      "cam_setfollowheight",
      "cam_smoothreset",
      "viewport_clampfov",
      "viewport_geteffectivesize",
      "viewport_getfov",
      "viewport_getzoom",
      "viewport_setfov",
      "viewport_setzoom"
    ],
    "CcOps": [
      "cc_addpinchflags",
      "cc_addswipeflags",
      "cc_callonresize",
      "cc_clearops",
      "cc_clearscripthooks",
      "cc_create",
      "cc_delete",
      "cc_deleteall",
      "cc_delpinchflags",
      "cc_delswipeflags",
      "cc_discardGestureHook",
      "cc_dragpickup",
      "cc_find",
      "cc_get2dangle",
      "cc_getcharindexatpos",
      "cc_getcharposatindex",
      "cc_getcolour",
      "cc_getfontgraphic",
      "cc_getfontmetrics",
      "cc_getgraphic",
      "cc_getgraphicdimensions",
      "cc_getheight",
      "cc_gethide",
      "cc_getid",
      "cc_getinvcount",
      "cc_getinvobject",
      "cc_getlayer",
      "cc_getmodel",
      "cc_getmodelangle_x",
      "cc_getmodelangle_y",
      "cc_getmodelangle_z",
      "cc_getmodelxof",
      "cc_getmodelyof",
      "cc_getmodelzoom",
      "cc_getop",
      "cc_getopbase",
      "cc_getscrollheight",
      "cc_getscrollwidth",
      "cc_getscrollx",
      "cc_getscrolly",
      "cc_gettargetmask",
      "cc_gettext",
      "cc_gettrans",
      "cc_getwidth",
      "cc_getx",
      "cc_gety",
      "cc_npc_setcustombodymodel",
      "cc_npc_setcustombodymodel_transformed",
      "cc_npc_setcustomheadmodel",
      "cc_npc_setcustomrecol",
      "cc_npc_setcustomretex",
      "cc_param",
      "cc_resetlinkplayer",
      "cc_resetmodellighting",
      "cc_resume_pausebutton",
      "cc_sendto",
      "cc_set2dangle",
      "cc_setalpha",
      "cc_setaspect",
      "cc_setclickmask",
      "cc_setcolour",
      "cc_setdragdeadtime",
      "cc_setdragdeadzone",
      "cc_setdraggable",
      "cc_setdragrenderbehaviour",
      "cc_setfill",
      "cc_setfontmono",
      "cc_setgraphic",
      "cc_setgraphicshadow",
      "cc_setheld",
      "cc_sethflip",
      "cc_sethide",
      "cc_setlinedirection",
      "cc_setlinewid",
      "cc_setlinkactiveclanchannel",
      "cc_setlinkfriend",
      "cc_setlinkfriendchat",
      "cc_setlinkplayergroup",
      "cc_setmaxlines",
      "cc_setmodel",
      "cc_setmodelangle",
      "cc_setmodelanim",
      "cc_setmodellighting",
      "cc_setmodelorigin",
      "cc_setmodelorthog",
      "cc_setmodeltint",
      "cc_setmodelzoom",
      "cc_setmouseovercursor",
      "cc_setnoclickthrough",
      "cc_setnpchead",
      "cc_setnpcmodel",
      "cc_setobject",
      "cc_setobject_alwaysnum",
      "cc_setobject_nonum",
      "cc_setobject_wearcol",
      "cc_setobject_wearcol_alwaysnum",
      "cc_setobject_wearcol_nonum",
      "cc_setoncameraupdatetransmit",
      "cc_setoncamfinished",
      "cc_setonchattransmit",
      "cc_setonclanchanneltransmit",
      "cc_setonclansettingstransmit",
      "cc_setonclantransmit",
      "cc_setonclick",
      "cc_setonclickrepeat",
      "cc_setondialogabort",
      "cc_setondrag",
      "cc_setondragcomplete",
      "cc_setondragcomplete_alias",
      "cc_setonfriendtransmit",
      "cc_setongamepadaxis",
      "cc_setongamepadbutton",
      "cc_setongamepadbuttonheld",
      "cc_setongamepadtrigger",
      "cc_setonhold",
      "cc_setonhorizontalpinch",
      "cc_setonhorizontalswipe",
      "cc_setoninvtransmit",
      "cc_setonkey",
      "cc_setonmisctransmit",
      "cc_setonmouseleave",
      "cc_setonmouseover",
      "cc_setonmouserepeat",
      "cc_setonop",
      "cc_setonopt",
      "cc_setonplayergrouptransmit",
      "cc_setonplayergroupvarptransmit",
      "cc_setonrelease",
      "cc_setonresize",
      "cc_setonscrollwheel",
      "cc_setonstattransmit",
      "cc_setonstocktransmit",
      "cc_setonsubchange",
      "cc_setontargetenter",
      "cc_setontargetleave",
      "cc_setontimer",
      "cc_setonvarclantransmit",
      "cc_setonvarcstrtransmit",
      "cc_setonvarctransmit",
      "cc_setonvartransmit",
      "cc_setonverticalpinch",
      "cc_setonverticalswipe",
      "cc_setop",
      "cc_setopbase",
      "cc_setopchar",
      "cc_setopcursor",
      "cc_setopkey",
      "cc_setopkeyignoreheld",
      "cc_setopkeyrate",
      "cc_setoptchar",
      "cc_setoptkey",
      "cc_setoptkeyignoreheld",
      "cc_setoptkeyrate",
      "cc_setoutline",
      "cc_setparam",
      "cc_setparam_int",
      "cc_setparam_string",
      "cc_setpausetext",
      "cc_setpinchdeadzone",
      "cc_setpinchflags",
      "cc_setplayerhead_self",
      "cc_setplayermodel",
      "cc_setplayermodel_self",
      "cc_setposition",
      "cc_setrecol",
      "cc_setretex",
      "cc_setscrollpos",
      "cc_setscrollsize",
      "cc_setsize",
      "cc_setsubtractinsets",
      "cc_setswipedeadtime",
      "cc_setswipedeadzone",
      "cc_setswipeflags",
      "cc_settargetcursors",
      "cc_settargetopcursor",
      "cc_settargetverb",
      "cc_settext",
      "cc_settextalign",
      "cc_settextantimacro",
      "cc_settextfont",
      "cc_settextshadow",
      "cc_settiling",
      "cc_settrans",
      "cc_setvflip",
      "cc_triggerop"
    ],
    "ChatOps": [
      "activechatphrase_prepare",
      "activechatphrase_send",
      "activechatphrase_sendprivate",
      "activechatphrase_setdynamicint",
      "activechatphrase_setdynamicobj",
      "chat_clear",
      "chat_getfilter_private",
      "chat_getfilter_public",
      "chat_getfilter_trade",
      "chat_gethistory_bytypeandline",
      "chat_gethistory_byuid",
      "chat_gethistorylength",
      "chat_getnextuid",
      "chat_getprevuid",
      "chat_lastuid",
      "chat_playername",
      "chat_playername_unfiltered",
      "chat_sendabusereport",
      "chat_sendprivate",
      "chat_sendpublic",
      "chat_setfilter",
      "chat_setmode",
      "chatcat_findphrasebyshortcut",
      "chatcat_findsubcatbyshortcut",
      "chatcat_getdesc",
      "chatcat_getphrase",
      "chatcat_getphrasecount",
      "chatcat_getphraseshortcut",
      "chatcat_getsubcat",
      "chatcat_getsubcatcount",
      "chatcat_getsubcatshortcut",
      "chatphrase_find",
      "chatphrase_findnext",
      "chatphrase_findrestart",
      "chatphrase_getautoresponse",
      "chatphrase_getautoresponsecount",
      "chatphrase_getdynamiccommand",
      "chatphrase_getdynamiccommandcount",
      "chatphrase_getdynamiccommandparam_enum",
      "chatphrase_gettext"
    ],
    "ConfigOps": [
      "_enum",
      "bas_getanim_ready",
      "enum_getoutputcount",
      "enum_getreversecount",
      "enum_getreversecount_string",
      "enum_getreverseindex",
      "enum_getreverseindex_string",
      "enum_hasoutput",
      "enum_hasoutput_string",
      "enum_string",
      "lc_param",
      "nc_param",
      "oc_category",
      "oc_cert",
      "oc_cost",
      "oc_find",
      "oc_findnext",
      "oc_findrestart",
      "oc_hasvarobj",
      "oc_icursor",
      "oc_id",
      "oc_iop",
      "oc_members",
      "oc_minimenu_colour",
      "oc_minimenu_colour_overridden",
      "oc_name",
      "oc_op",
      "oc_param",
      "oc_placeholder",
      "oc_shard",
      "oc_shardcount",
      "oc_stackable",
      "oc_tradeable",
      "oc_uncert",
      "oc_unshard",
      "oc_wearpos",
      "oc_wearpos2",
      "oc_wearpos3",
      "struct_param"
    ],
    "CoreOps": [
      "branch",
      "branch_equals",
      "branch_greater_than",
      "branch_greater_than_or_equals",
      "branch_if_false",
      "branch_if_true",
      "branch_less_than",
      "branch_less_than_or_equals",
      "branch_not",
      "define_array",
      "gosub_with_params",
      "join_string",
      "pop_array",
      "pop_int_discard",
      "pop_int_local",
      "pop_long_discard",
      "pop_long_local",
      "pop_string_discard",
      "pop_string_local",
      "pop_var",
      "pop_varbit",
      "push_array",
      "push_constant_int",
      "push_constant_string",
      "push_int_local",
      "push_long_constant",
      "push_long_local",
      "push_string_local",
      "push_var",
      "push_varbit"
    ],
    "DbOps": [
      "db_find",
      "db_find_get",
      "db_find_refine",
      "db_findnext",
      "db_getfield",
      "db_getfieldcount",
      "db_getrowtable",
      "db_listall"
    ],
    "DetailOps": [
      "detail_ambientocclusion",
      "detail_animdetail",
      "detail_anisotropicfiltering",
      "detail_antialiasing",
      "detail_antialiasing_default",
      "detail_antialiasingmode",
      "detail_bgsoundvol",
      "detail_bloom",
      "detail_brightness",
      "detail_buildarea",
      "detail_cpuusage",
      "detail_customcursors",
      "detail_diskcachesize",
      "detail_dof",
      "detail_drawdistance",
      "detail_flickering_on",
      "detail_fog_on",
      "detail_gamerenderscale",
      "detail_groundblending",
      "detail_grounddecor_on",
      "detail_hardshadows",
      "detail_idleanims",
      "detail_idleanims_many",
      "detail_interfacescale",
      "detail_lightdetail_high",
      "detail_lightingquality",
      "detail_loadingscreentype",
      "detail_loginvol",
      "detail_maxbackgroundfps",
      "detail_maxforegroundfps",
      "detail_maxscreensize",
      "detail_musicvol",
      "detail_particles",
      "detail_reflections",
      "detail_removeroofs_option",
      "detail_removeroofs_option_override",
      "detail_shadowquality",
      "detail_shadows",
      "detail_skydetail",
      "detail_soundvol",
      "detail_speechvol",
      "detail_spotshadows_on",
      "detail_stereo",
      "detail_texturing",
      "detail_toolkit",
      "detail_toolkit_default",
      "detail_volumetriclighting",
      "detail_vsync",
      "detail_waterdetail_high",
      "detailcanmod_ambientocclusion",
      "detailcanmod_animdetail",
      "detailcanmod_anisotropicfiltering",
      "detailcanmod_antialiasing",
      "detailcanmod_antialiasingmode",
      "detailcanmod_bloom",
      "detailcanmod_buildarea",
      "detailcanmod_dof",
      "detailcanmod_fog",
      "detailcanmod_gamerenderscale",
      "detailcanmod_groundblending",
      "detailcanmod_grounddecor",
      "detailcanmod_hardshadows",
      "detailcanmod_interfacescale",
      "detailcanmod_lightingquality",
      "detailcanmod_maxbackgroundfps",
      "detailcanmod_maxforegroundfps",
      "detailcanmod_maxscreensize",
      "detailcanmod_orthographic",
      "detailcanmod_particles",
      "detailcanmod_reflections",
      "detailcanmod_shadowquality",
      "detailcanmod_shadows",
      "detailcanmod_skydetail",
      "detailcanmod_spotshadows",
      "detailcanmod_texturing",
      "detailcanmod_toolkit_default",
      "detailcanmod_volumetriclighting",
      "detailcanmod_vsync",
      "detailcanmod_waterdetail",
      "detailcanset_ambientocclusion",
      "detailcanset_animdetail",
      "detailcanset_anisotropicfiltering",
      "detailcanset_antialiasing",
      "detailcanset_antialiasingmode",
      "detailcanset_bloom",
      "detailcanset_buildarea",
      "detailcanset_dof",
      "detailcanset_fog",
      "detailcanset_gamerenderscale",
      "detailcanset_groundblending",
      "detailcanset_grounddecor",
      "detailcanset_hardshadows",
      "detailcanset_interfacescale",
      "detailcanset_lightingquality",
      "detailcanset_maxbackgroundfps",
      "detailcanset_maxforegroundfps",
      "detailcanset_maxscreensize",
      "detailcanset_orthographic",
      "detailcanset_particles",
      "detailcanset_reflections",
      "detailcanset_shadowquality",
      "detailcanset_shadows",
      "detailcanset_skydetail",
      "detailcanset_spotshadows",
      "detailcanset_texturing",
      "detailcanset_toolkit_default",
      "detailcanset_volumetriclighting",
      "detailcanset_vsync",
      "detailcanset_waterdetail",
      "detailget_ambientocclusion",
      "detailget_animdetail",
      "detailget_anisotropicfiltering",
      "detailget_antialiasing",
      "detailget_antialiasing_default",
      "detailget_antialiasingmode",
      "detailget_bgsoundvol",
      "detailget_bloom",
      "detailget_brightness",
      "detailget_buildarea",
      "detailget_canchoosesafemode",
      "detailget_chosesafemode",
      "detailget_cpuusage",
      "detailget_customcursors",
      "detailget_diskcachesize",
      "detailget_dof",
      "detailget_drawdistance",
      "detailget_flickering_on",
      "detailget_fog_on",
      "detailget_gamerenderscale",
      "detailget_groundblending",
      "detailget_grounddecor_on",
      "detailget_hardshadows",
      "detailget_idleanims",
      "detailget_idleanims_many",
      "detailget_interfacescale",
      "detailget_lightdetail_high",
      "detailget_lightingquality",
      "detailget_loadingscreentype",
      "detailget_loginvol",
      "detailget_maxbackgroundfps",
      "detailget_maxdiskcachesize",
      "detailget_maxforegroundfps",
      "detailget_maxscreensize",
      "detailget_mindiskcachesize",
      "detailget_musicvol",
      "detailget_orthographic",
      "detailget_particles",
      "detailget_performance_metric",
      "detailget_recommendeddiskcachesize",
      "detailget_reflections",
      "detailget_removeroofs_option",
      "detailget_safemode",
      "detailget_shadowquality",
      "detailget_shadows",
      "detailget_skydetail",
      "detailget_soundvol",
      "detailget_speechvol",
      "detailget_spotshadows_on",
      "detailget_stereo",
      "detailget_texturing",
      "detailget_toolkit",
      "detailget_toolkit_default",
      "detailget_volumetriclighting",
      "detailget_vsync",
      "detailget_waterdetail_high"
    ],
    "IfOps": [
      "if_addpinchflags",
      "if_addswipeflags",
      "if_callonresize",
      "if_clearops",
      "if_clearscripthooks",
      "if_close",
      "if_closesubclient",
      "if_debug_button1",
      "if_debug_button10",
      "if_debug_button2",
      "if_debug_button3",
      "if_debug_button4",
      "if_debug_button5",
      "if_debug_button6",
      "if_debug_button7",
      "if_debug_button8",
      "if_debug_button9",
      "if_debug_getcomcount",
      "if_debug_getcomname",
      "if_debug_getname",
      "if_debug_getopenifcount",
      "if_debug_getopenifid",
      "if_debug_getservertriggers",
      "if_debug_target",
      "if_delpinchflags",
      "if_delswipeflags",
      "if_discardGestureHook",
      "if_dragpickup",
      "if_find",
      "if_get2dangle",
      "if_get_gamescreen",
      "if_getcharindexatpos",
      "if_getcharposatindex",
      "if_getcolour",
      "if_getfontgraphic",
      "if_getfontmetrics",
      "if_getgraphic",
      "if_getgraphicdimensions",
      "if_getheight",
      "if_gethide",
      "if_getinvcount",
      "if_getinvobject",
      "if_getlayer",
      "if_getmodel",
      "if_getmodelangle_x",
      "if_getmodelangle_y",
      "if_getmodelangle_z",
      "if_getmodelxof",
      "if_getmodelyof",
      "if_getmodelzoom",
      "if_getnextsubid",
      "if_getop",
      "if_getopbase",
      "if_getparentlayer",
      "if_getscrollheight",
      "if_getscrollwidth",
      "if_getscrollx",
      "if_getscrolly",
      "if_gettargetmask",
      "if_gettext",
      "if_gettop",
      "if_gettrans",
      "if_getwidth",
      "if_getx",
      "if_gety",
      "if_hassub",
      "if_hassubmodal",
      "if_hassuboverlay",
      "if_npc_setcustombodymodel",
      "if_npc_setcustombodymodel_transformed",
      "if_npc_setcustomheadmodel",
      "if_npc_setcustomrecol",
      "if_npc_setcustomretex",
      "if_opensubclient",
      "if_resetlinkplayer",
      "if_resetmodellighting",
      "if_resume_pausebutton",
      "if_sendto",
      "if_set2dangle",
      "if_set_gamescreen_enabled",
      "if_setalpha",
      "if_setaspect",
      "if_setclickmask",
      "if_setcolour",
      "if_setdragdeadtime",
      "if_setdragdeadzone",
      "if_setdraggable",
      "if_setdragrenderbehaviour",
      "if_setfill",
      "if_setfontmono",
      "if_setgraphic",
      "if_setgraphicshadow",
      "if_setheld",
      "if_sethflip",
      "if_sethide",
      "if_setlinedirection",
      "if_setlinewid",
      "if_setlinkactiveclanchannel",
      "if_setlinkfriend",
      "if_setlinkfriendchat",
      "if_setlinkplayergroup",
      "if_setmaxlines",
      "if_setmodel",
      "if_setmodelangle",
      "if_setmodelanim",
      "if_setmodellighting",
      "if_setmodelorigin",
      "if_setmodelorthog",
      "if_setmodeltint",
      "if_setmodelzoom",
      "if_setmouseovercursor",
      "if_setnoclickthrough",
      "if_setnpchead",
      "if_setnpcmodel",
      "if_setobject",
      "if_setobject_alwaysnum",
      "if_setobject_nonum",
      "if_setobject_wearcol",
      "if_setobject_wearcol_alwaysnum",
      "if_setobject_wearcol_nonum",
      "if_setoncameraupdatetransmit",
      "if_setoncamfinished",
      "if_setonchattransmit",
      "if_setonclanchanneltransmit",
      "if_setonclansettingstransmit",
      "if_setonclantransmit",
      "if_setonclick",
      "if_setonclickrepeat",
      "if_setondialogabort",
      "if_setondrag",
      "if_setondragcomplete",
      "if_setondragcomplete_alias",
      "if_setonfriendtransmit",
      "if_setongamepadaxis",
      "if_setongamepadbutton",
      "if_setongamepadbuttonheld",
      "if_setongamepadtrigger",
      "if_setonhold",
      "if_setonhorizontalpinch",
      "if_setonhorizontalswipe",
      "if_setoninvtransmit",
      "if_setonkey",
      "if_setonmisctransmit",
      "if_setonmouseleave",
      "if_setonmouseover",
      "if_setonmouserepeat",
      "if_setonop",
      "if_setonopt",
      "if_setonplayergrouptransmit",
      "if_setonplayergroupvarptransmit",
      "if_setonrelease",
      "if_setonresize",
      "if_setonscrollwheel",
      "if_setonstattransmit",
      "if_setonstocktransmit",
      "if_setonsubchange",
      "if_setontargetenter",
      "if_setontargetleave",
      "if_setontimer",
      "if_setonvarclantransmit",
      "if_setonvarcstrtransmit",
      "if_setonvarctransmit",
      "if_setonvartransmit",
      "if_setonverticalpinch",
      "if_setonverticalswipe",
      "if_setop",
      "if_setopbase",
      "if_setopchar",
      "if_setopcursor",
      "if_setopkey",
      "if_setopkeyignoreheld",
      "if_setopkeyrate",
      "if_setoptchar",
      "if_setoptkey",
      "if_setoptkeyignoreheld",
      "if_setoptkeyrate",
      "if_setoutline",
      "if_setparam_int",
      "if_setparam_string",
      "if_setpausetext",
      "if_setpinchdeadzone",
      "if_setpinchflags",
      "if_setplayerhead_self",
      "if_setplayermodel",
      "if_setplayermodel_self",
      "if_setposition",
      "if_setrecol",
      "if_setretex",
      "if_setscrollpos",
      "if_setscrollsize",
      "if_setsize",
      "if_setsubtractinsets",
      "if_setswipedeadtime",
      "if_setswipedeadzone",
      "if_setswipeflags",
      "if_settargetcursors",
      "if_settargetopcursor",
      "if_settargetverb",
      "if_settext",
      "if_settextalign",
      "if_settextantimacro",
      "if_settextfont",
      "if_settextshadow",
      "if_settiling",
      "if_settrans",
      "if_setvflip",
      "if_triggerop"
    ],
    "InvOps": [
      "inv_freespace",
      "inv_getnum",
      "inv_getobj",
      "inv_getvar",
      "inv_size",
      "inv_stockbase",
      "inv_total",
      "inv_totalcat",
      "inv_totalparam",
      "inv_totalparam_stack"
    ],
    "MiscOps": [
      "_return",
      "_switch",
      "abort_dialog",
      "abs",
      "activeclanchannel_find_affined",
      "activeclanchannel_find_listened",
      "activeclanchannel_getclanname",
      "activeclanchannel_getrankkick",
      "activeclanchannel_getranktalk",
      "activeclanchannel_getsorteduserslot",
      "activeclanchannel_getusercount",
      "activeclanchannel_getuserdisplayname",
      "activeclanchannel_getuserrank",
      "activeclanchannel_getuserslot",
      "activeclanchannel_getuserworld",
      "activeclanchannel_kickuser",
      "activeclansettings_find_affined",
      "activeclansettings_find_listened",
      "activeclansettings_getaffinedcount",
      "activeclansettings_getaffineddisplayname",
      "activeclansettings_getaffinedextrainfo",
      "activeclansettings_getaffinedjoinruneday",
      "activeclansettings_getaffinedmuted",
      "activeclansettings_getaffinedrank",
      "activeclansettings_getaffinedslot",
      "activeclansettings_getallowunaffined",
      "activeclansettings_getbannedcount",
      "activeclansettings_getbanneddisplayname",
      "activeclansettings_getclanname",
      "activeclansettings_getcoinshare",
      "activeclansettings_getcurrentowner_slot",
      "activeclansettings_getrankkick",
      "activeclansettings_getranklootshare",
      "activeclansettings_getranktalk",
      "activeclansettings_getreplacementowner_slot",
      "activeclansettings_getsortedaffinedslot",
      "add",
      "addpercent",
      "affiliate",
      "and",
      "append",
      "append_char",
      "append_num",
      "append_signnum",
      "applet_hasfocus",
      "applyDisplayPreference",
      "array_sort",
      "atan2_deg",
      "automatedtestflags",
      "autosetup_blackflaglast",
      "autosetup_dosetup",
      "autosetup_dosetupstatus",
      "autosetup_getlevel",
      "autosetup_setcustom",
      "autosetup_sethigh",
      "autosetup_setlow",
      "autosetup_setmedium",
      "autosetup_setmin",
      "autosetup_setultra",
      "basecolour",
      "baseidkit",
      "basematerial",
      "battery_getlevelpercent",
      "battery_ischarging",
      "bitcount",
      "bug_report",
      "can_run_java_client",
      "cancel_interface_drag",
      "cc_getparentlayer",
      "char_isalpha",
      "char_isalphanumeric",
      "char_isnumeric",
      "char_isprintable",
      "char_isvalid",
      "char_tolowercase",
      "char_touppercase",
      "clearbit",
      "clearbit_range",
      "clientclock",
      "clienttype",
      "comlevel_active",
      "compare",
      "coord",
      "coord_fine",
      "coord_finetogrid",
      "coord_gridtofine",
      "coordlevel_fine",
      "coordx",
      "coordx_fine",
      "coordy",
      "coordy_fine",
      "coordz",
      "coordz_fine",
      "cos_deg",
      "create_availablerequest",
      "create_connect_reply",
      "create_connectrequest",
      "create_createrequest",
      "create_email_validate_reply",
      "create_get_email",
      "create_name_availablerequest",
      "create_name_validate_reply",
      "create_reply",
      "create_setunder13",
      "create_step_reached",
      "create_suggest_name_reply",
      "create_suggest_name_request",
      "create_under13",
      "date_isleapyear",
      "date_minutes",
      "date_minutes_fromruneday",
      "date_runeday",
      "date_runeday_fromdate",
      "date_runeday_todate",
      "date_year",
      "defaultminimenu",
      "discardCurrentSwipeSettingArg",
      "discardDetailSettingPair",
      "discardDisplayBounds",
      "discardDisplaySettingPair",
      "discardDragResizePair",
      "discardDragTarget",
      "discardDragTargetPair",
      "discardFontArg",
      "discardFourInterfaceArgs",
      "discardInterfaceArg",
      "discardInterfaceTargetArg",
      "discardLogoutArg",
      "discardNotificationGroup",
      "discardThreeInterfaceArgs",
      "discardWorldMapMenuAction",
      "divide",
      "docheat",
      "email_validation_add_new_address",
      "email_validation_change_address",
      "email_validation_submit_code",
      "emoji_add",
      "emoji_enable_auto_chatline",
      "emoji_remove",
      "emoji_removeall",
      "emoji_substitute",
      "escape",
      "facing_fine",
      "force_interface_drag",
      "format_datetime_from_minutes",
      "formatminimenu",
      "fps_stats",
      "frombilling",
      "fromdate",
      "fullscreen_enter",
      "fullscreen_exit",
      "fullscreen_getmode",
      "fullscreen_lastmode",
      "fullscreen_modecount",
      "gender",
      "get_active_minimenu_entry",
      "get_col_tag",
      "get_currentcursor",
      "get_displayname_withextras",
      "get_entity_bounding_box",
      "get_entity_overlay_height",
      "get_entity_say",
      "get_entity_screen_position",
      "get_loc_bounding_box",
      "get_loc_overlay_height",
      "get_loc_screen_position",
      "get_minimenu_length",
      "get_minimenu_target",
      "get_mousebuttons",
      "get_mousex",
      "get_mousey",
      "get_npc_name",
      "get_npc_stat",
      "get_npc_vislevel",
      "get_obj_bounding_box",
      "get_obj_overlay_height",
      "get_obj_screen_position",
      "get_second_minimenu_entry",
      "get_selfyangle",
      "getbit_range",
      "getclipboard",
      "getdefaultwindowmode",
      "getgridcoordrelativetocamera",
      "getwindowmode",
      "has_html5",
      "has_nxt",
      "hsvtorgb",
      "interface_getpickingradius",
      "interface_setpickingradius",
      "interpolate",
      "invother_getnum",
      "invother_getobj",
      "invother_getvar",
      "invother_total",
      "invpow",
      "is_gamescreen_state",
      "is_npc_active",
      "is_npc_visible",
      "is_targeted_entity",
      "keyheld_alt",
      "keyheld_ctrl",
      "keyheld_shift",
      "lastlogin",
      "lobby_entergame",
      "lobby_entergamereply",
      "lobby_enterlobby",
      "lobby_enterlobby_social_network",
      "lobby_enterlobby_sso",
      "lobby_enterlobbyreply",
      "lobby_leavelobby",
      "login_accountappeal",
      "login_ban_duration",
      "login_cancel",
      "login_continue",
      "login_disallowresult",
      "login_disallowtrigger",
      "login_hoptime",
      "login_inprogress",
      "login_last_transfer_reply",
      "login_queue_position",
      "login_reply",
      "login_request",
      "login_request_social_network",
      "login_resetreply",
      "logout_getreason",
      "long_branch_equals",
      "long_branch_greater_than",
      "long_branch_greater_than_or_equals",
      "long_branch_less_than",
      "long_branch_less_than_or_equals",
      "long_branch_not",
      "lowercase",
      "map_build_complete",
      "map_isowner",
      "map_lang",
      "map_loadedpercent",
      "map_loadingscreen_isopen",
      "map_loadingscreen_settriggerpercent",
      "map_members",
      "map_preload",
      "map_quickchat",
      "map_world",
      "marketing_init",
      "marketing_sendevent",
      "max",
      "mec_category",
      "mec_param",
      "mec_sprite",
      "mec_text",
      "mec_textsize",
      "mes",
      "mes_typed",
      "min",
      "minimenu_close",
      "minimenuopen",
      "modulo",
      "movecoord",
      "movecoord_fine",
      "movescripted",
      "multiply",
      "noopAutosetupCommand",
      "noopDisplayCommand",
      "noopInterfaceCommand",
      "noopLicenseCommand",
      "noopTargetModeCommand",
      "noopWalkMarkerCommand",
      "noopWorldMapCommand",
      "not",
      "notifications_cancellocal",
      "notifications_init",
      "notifications_opensettings",
      "notifications_sendgroupedlocal",
      "notifications_sendlocal",
      "notify_accountcreated",
      "notify_accountcreatestarted",
      "npc_find_active_minimenu_entry",
      "npc_type",
      "opcount",
      "openurl",
      "openurl_nologin",
      "openurl_shim",
      "openurlraw",
      "opplayer",
      "opplayert",
      "or",
      "os_driver_outdated",
      "os_driver_vendor",
      "os_isandroid",
      "os_isios",
      "os_islinux",
      "os_ismac",
      "os_iswindows",
      "os_physicalmemorysize",
      "paraheight",
      "paraline",
      "parawidth",
      "player_find_active_minimenu_entry",
      "playercountry",
      "playerdemo",
      "playermember",
      "playermod",
      "playermodlevel",
      "pow",
      "preload_download_complete",
      "preload_download_downloadedsize",
      "preload_download_rate",
      "preload_download_remainingsize",
      "preload_download_totalsize",
      "preload_percent",
      "preload_progress",
      "profile_cpu",
      "pushCanvasSize",
      "pushFontAvailable",
      "pushFontMetrics",
      "pushLicenseAvailable",
      "pushNotificationPermissionGranted",
      "pushNotificationUnavailable",
      "pushRuneScapeSetupValue",
      "pushShopUnavailable",
      "pushTargetModeUnavailable",
      "pushTargetModeZero",
      "pushUnsupportedCommandDefaults",
      "pushUnsupportedCommandTriple",
      "pushUnsupportedPairFalse",
      "pushUnsupportedPairFalseAlt",
      "pushUnsupportedPairFalseFifth",
      "pushUnsupportedPairFalseFourth",
      "pushUnsupportedPairFalseThird",
      "pushUnsupportedQuadFalse",
      "pushWorldMapUnavailable",
      "pushZeroInsets",
      "quit",
      "random",
      "random_sound_pitch",
      "randominc",
      "reboottimer",
      "removetags",
      "resend_uid_passport_request",
      "resume_clanforumqfcdialog",
      "resume_countdialog",
      "resume_hsldialog",
      "resume_namedialog",
      "resume_objdialog",
      "resume_stringdialog",
      "runenergy_visible",
      "runjavascript",
      "runweight_visible",
      "saveRuneScapeSetup",
      "scale",
      "self_player_uid",
      "seq_param",
      "seqlength",
      "setbit",
      "setbit_range",
      "setbit_range_toint",
      "setdefaultcursors",
      "setdefaultwindowmode",
      "setgender",
      "sethardcodedopcursors",
      "setobj",
      "setsubmenuminlength",
      "setup_messagebox",
      "setwalkmarker",
      "setwindowmode",
      "shader_preload_allow",
      "shader_preload_percent",
      "shader_preload_throttle",
      "shop_applypendingtransactions",
      "shop_getcategorycount",
      "shop_getcategorydescription",
      "shop_getcategoryid",
      "shop_getindexforcategoryid",
      "shop_getindexforcategoryname",
      "shop_getproductcount",
      "shop_getproductdetails",
      "shop_isproductavailable",
      "shop_isproductrecommended",
      "shop_open",
      "shop_opencategories",
      "shop_requestdata",
      "shop_requestdatastatus",
      "show_software_license",
      "sin_deg",
      "spline_addpoint",
      "spline_length",
      "spline_new",
      "sqrt",
      "sso_available",
      "sso_displayname",
      "staffmodlevel",
      "stockmarket_getoffercompletedcount",
      "stockmarket_getoffercompletedgold",
      "stockmarket_getoffercount",
      "stockmarket_getofferitem",
      "stockmarket_getofferprice",
      "stockmarket_getoffertype",
      "stockmarket_isofferadding",
      "stockmarket_isofferempty",
      "stockmarket_isofferfinished",
      "stockmarket_isofferstable",
      "string_distance",
      "string_indexof_char",
      "string_indexof_string",
      "string_length",
      "stringwidth",
      "substring",
      "targetmode_active",
      "targetmode_cancel",
      "testbit",
      "text_gender",
      "text_switch",
      "togglebit",
      "tostring",
      "tostring_localised",
      "urlencode",
      "userdetail_dob",
      "userdetail_lobby_ccexpiry",
      "userdetail_lobby_dobrequested",
      "userdetail_lobby_emailstatus",
      "userdetail_lobby_graceexpiry",
      "userdetail_lobby_jcoins_balance",
      "userdetail_lobby_lastloginaddress",
      "userdetail_lobby_lastloginday",
      "userdetail_lobby_loyalty_balance",
      "userdetail_lobby_membership",
      "userdetail_lobby_membersstats",
      "userdetail_lobby_playage",
      "userdetail_lobby_recoveryday",
      "userdetail_lobby_unreadmessages",
      "userdetail_quickchat",
      "userflowflags",
      "video_advert_allow_skip",
      "video_advert_force_remove",
      "video_advert_has_finished",
      "video_advert_play",
      "window_getinsets",
      "worldlist_autoworld",
      "worldlist_fetch",
      "worldlist_next",
      "worldlist_pingworlds",
      "worldlist_sort",
      "worldlist_specific",
      "worldlist_specific_thisworld",
      "worldlist_start",
      "worldlist_switch",
      "writeconsole"
    ],
    "SocialOps": [
      "affinedclansettings_addbanned_fromchannel",
      "affinedclansettings_setmuted_fromchannel",
      "clan_getchatcount",
      "clan_getchatdisplayname",
      "clan_getchatminkick",
      "clan_getchatownername",
      "clan_getchatrank",
      "clan_getchatusername",
      "clan_getchatusername_unfiltered",
      "clan_getchatuserrank",
      "clan_getchatuserworld",
      "clan_getchatuserworldname",
      "clan_isself",
      "clan_joinchat",
      "clan_kickuser",
      "clan_leavechat",
      "clanforumqfc_tostring",
      "clanprofile_find",
      "friend_add",
      "friend_count",
      "friend_del",
      "friend_getname",
      "friend_getnotes",
      "friend_getrank",
      "friend_getslotfromname",
      "friend_getworld",
      "friend_getworldflags",
      "friend_getworldname",
      "friend_is_referred",
      "friend_is_referrer",
      "friend_platform",
      "friend_setnotes",
      "friend_setrank",
      "friend_test",
      "ignore_add",
      "ignore_add_temp",
      "ignore_count",
      "ignore_del",
      "ignore_getname",
      "ignore_getname_unfiltered",
      "ignore_getnotes",
      "ignore_getslotfromname",
      "ignore_is_temp",
      "ignore_setnotes",
      "ignore_test",
      "player_group_banned_count",
      "player_group_banned_get_displayname",
      "player_group_find",
      "player_group_get_create_mins_since_epoch",
      "player_group_get_create_seconds_to_now",
      "player_group_get_displayname",
      "player_group_get_max_size",
      "player_group_get_overall_status",
      "player_group_get_owner_slot",
      "player_group_is_members_only",
      "player_group_member_count",
      "player_group_member_get_displayname",
      "player_group_member_get_join_xp",
      "player_group_member_get_last_seen_node_id",
      "player_group_member_get_rank",
      "player_group_member_get_same_world_var",
      "player_group_member_get_status",
      "player_group_member_get_team",
      "player_group_member_is_member",
      "player_group_member_is_online",
      "player_group_member_is_owner"
    ],
    "StatOps": [
      "stat",
      "stat_base",
      "stat_base_actual",
      "stat_visible_xp",
      "stat_visible_xp_actual"
    ],
    "TelemetryOps": [
      "telemetry_get_column_count",
      "telemetry_get_column_id",
      "telemetry_get_column_index",
      "telemetry_get_grid_value",
      "telemetry_get_group_count",
      "telemetry_get_group_id",
      "telemetry_get_group_index",
      "telemetry_get_row_count",
      "telemetry_get_row_id",
      "telemetry_get_row_index",
      "telemetry_is_grid_processor_set",
      "telemetry_is_row_pinned"
    ],
    "WorldMapOps": [
      "worldmap_3dview_active",
      "worldmap_3dview_disable",
      "worldmap_3dview_enable",
      "worldmap_3dview_getcoordfine",
      "worldmap_3dview_getloddistance",
      "worldmap_3dview_getscreenposition",
      "worldmap_3dview_gettextfont",
      "worldmap_3dview_setlighting",
      "worldmap_3dview_setloddistance",
      "worldmap_3dview_settextfont",
      "worldmap_closemap",
      "worldmap_coordinmap",
      "worldmap_disableelement",
      "worldmap_disableelementcategory",
      "worldmap_disableelements",
      "worldmap_disabletextsize",
      "worldmap_disabletype",
      "worldmap_findnearestelement",
      "worldmap_flashelement",
      "worldmap_flashelementcategory",
      "worldmap_getcategorypriority",
      "worldmap_getconfigbounds",
      "worldmap_getconfigorigin",
      "worldmap_getconfigsize",
      "worldmap_getconfigzoom",
      "worldmap_getcurrentmap",
      "worldmap_getdisableelement",
      "worldmap_getdisableelementcategory",
      "worldmap_getdisableelements",
      "worldmap_getdisabletextsize",
      "worldmap_getdisabletype",
      "worldmap_getdisplaycoord",
      "worldmap_getdisplayposition",
      "worldmap_getmap",
      "worldmap_getmapname",
      "worldmap_getsize",
      "worldmap_getsourcecoord",
      "worldmap_getsourceposition",
      "worldmap_getzoom",
      "worldmap_isloaded",
      "worldmap_jumptodisplaycoord",
      "worldmap_jumptodisplaycoord_instant",
      "worldmap_jumptosourcecoord",
      "worldmap_jumptosourcecoord_instant",
      "worldmap_listelement_next",
      "worldmap_listelement_start",
      "worldmap_perpetualflash",
      "worldmap_setcategorypriority",
      "worldmap_setflashloops",
      "worldmap_setflashloops_default",
      "worldmap_setflashtics",
      "worldmap_setflashtics_default",
      "worldmap_setmap",
      "worldmap_setmap_coord",
      "worldmap_setmap_coord_override",
      "worldmap_setzoom",
      "worldmap_stopcurrentflashes"
    ]
  }
}
